{
  "publicPath": "/_nuxt/",
  "all": [
    "../server/index.spa.html",
    "../server/index.ssr.html",
    "05a4b68.js",
    "1cf3568.js",
    "4667749.js",
    "496033a.js",
    "4c23d8c.js",
    "8dc57c9.js",
    "LICENSES",
    "a4d87eb.js",
    "b356900.js",
    "f4d0dd2.js",
    "img/mk-icon-instagram.c8f8ee2.svg",
    "img/mk-logo-side.48fae47.svg",
    "img/mk-logo.e1f9657.svg"
  ],
  "initial": [
    "8dc57c9.js",
    "4667749.js",
    "4c23d8c.js"
  ],
  "async": [
    "05a4b68.js",
    "1cf3568.js",
    "496033a.js",
    "a4d87eb.js",
    "b356900.js",
    "f4d0dd2.js"
  ],
  "modules": {
    "14713817": [
      4
    ],
    "17461010": [
      4
    ],
    "23604129": [
      6,
      13,
      14,
      12
    ],
    "74828425": [
      4
    ],
    "80680402": [
      4
    ],
    "60d261ea": [
      6,
      13,
      14,
      12
    ],
    "143ffb02": [
      4
    ],
    "52c8bd1b": [
      4
    ],
    "95a67404": [
      4
    ],
    "50bb12cc": [
      4
    ],
    "536e2a6a": [
      4
    ],
    "ac6edfd8": [
      4
    ],
    "c4af9b40": [
      4
    ],
    "58211cfc": [
      4
    ],
    "78a649c6": [
      4
    ],
    "177f1e27": [
      4
    ],
    "0048ee20": [
      4
    ],
    "1845a3ea": [
      4
    ],
    "2bdf6484": [
      4
    ],
    "69aaba6e": [
      4
    ],
    "8be9d0fe": [
      4
    ],
    "1adc91ba": [
      4
    ],
    "aad98d6c": [
      4
    ],
    "467e8f8a": [
      4
    ],
    "075b7676": [
      4
    ],
    "af749f0e": [
      4
    ],
    "b4adaa3e": [
      4
    ],
    "3c41d29a": [
      4
    ],
    "56a77f90": [
      4
    ],
    "df2b3174": [
      4
    ],
    "2ee09b96": [
      4
    ],
    "7687a9a4": [
      4
    ],
    "3bf64a29": [
      6,
      13,
      14,
      12
    ],
    "7d10f84a": [
      6,
      13,
      14,
      12
    ],
    "13ccf1f0": [
      6,
      13,
      14,
      12
    ],
    "7aeb6b2a": [
      6,
      13,
      14,
      12
    ],
    "3d56775f": [
      6,
      13,
      14,
      12
    ],
    "7ffeef9a": [
      6,
      13,
      14,
      12
    ],
    "1192fa6f": [
      6,
      13,
      14,
      12
    ],
    "16fe1405": [
      6,
      13,
      14,
      12
    ],
    "49a91037": [
      6,
      13,
      14,
      12
    ],
    "9c777130": [
      6,
      13,
      14,
      12
    ],
    "e5188cec": [
      6,
      13,
      14,
      12
    ],
    "37d77444": [
      6,
      13,
      14,
      12
    ],
    "48203f28": [
      6,
      13,
      14,
      12
    ],
    "13e88e4c": [
      6,
      13,
      14,
      12
    ],
    "42aea9da": [
      6,
      13,
      14,
      12
    ],
    "fcb87cd4": [
      6,
      13,
      14,
      12
    ],
    "05f593d8": [
      6,
      13,
      14,
      12
    ],
    "8fb63df0": [
      6,
      13,
      14,
      12
    ],
    "596274df": [
      6,
      13,
      14,
      12
    ],
    "d37bde88": [
      6,
      13,
      14,
      12
    ],
    "2e591811": [
      6,
      13,
      14,
      12
    ],
    "4a985144": [
      6,
      13,
      14,
      12
    ],
    "7f26877e": [
      6,
      13,
      14,
      12
    ],
    "2aa82725": [
      6,
      13,
      14,
      12
    ],
    "079f13f8": [
      4
    ],
    "7e6a6288": [
      4
    ],
    "fa0253f2": [
      4
    ],
    "aaab8582": [
      4
    ],
    "5bf06752": [
      4
    ],
    "637fac2e": [
      4
    ],
    "faff17f8": [
      4
    ],
    "08976296": [
      4
    ],
    "212f91e3": [
      4
    ],
    "60bf160a": [
      4
    ],
    "082ba359": [
      4
    ],
    "c375faee": [
      6,
      13,
      14,
      12
    ],
    "135a30d4": [
      4
    ],
    "54d46d79": [
      4
    ],
    "00d497d4": [
      4
    ],
    "1ccd265c": [
      4
    ],
    "f8e8a6d4": [
      4
    ],
    "18eab1aa": [
      4
    ],
    "4384d70b": [
      4
    ],
    "2707acaa": [
      4
    ],
    "62295cb5": [
      4
    ],
    "3022458c": [
      4
    ],
    "40701fba": [
      4
    ],
    "4a2ad95a": [
      4
    ],
    "6dd8cded": [
      4
    ],
    "828f4d74": [
      4
    ],
    "80f2c20c": [
      4
    ],
    "3b651795": [
      4
    ],
    "047caa15": [
      4
    ],
    "1ca26f4e": [
      4
    ],
    "fc93e8b2": [
      4
    ],
    "436fadf1": [
      4
    ],
    "01593dd4": [
      4
    ],
    "c78f3ac6": [
      4
    ],
    "ddbffaac": [
      4
    ],
    "fd9a71ee": [
      4
    ],
    "2f33be16": [
      4
    ],
    "2f9b511d": [
      4
    ],
    "7970e094": [
      4
    ],
    "8ad73150": [
      4
    ],
    "af1f8b54": [
      4
    ],
    "0b5f0a56": [
      4
    ],
    "6d5c902d": [
      6,
      13,
      14,
      12
    ],
    "bbfe6536": [
      4
    ],
    "c1c6f944": [
      4
    ],
    "1dd4271a": [
      4
    ],
    "3af79662": [
      4
    ],
    "a97499be": [
      4
    ],
    "77f39edb": [
      4
    ],
    "68dd7994": [
      4
    ],
    "dc4d9610": [
      4
    ],
    "beb27bf0": [
      4
    ],
    "1a0859a0": [
      4
    ],
    "55b0635e": [
      4
    ],
    "cd5fc7f4": [
      4
    ],
    "77914d43": [
      4
    ],
    "563a60ce": [
      4
    ],
    "5fc6f1e4": [
      4
    ],
    "ba1722fe": [
      4
    ],
    "006e4864": [
      4
    ],
    "51cd57d6": [
      4
    ],
    "32200c9d": [
      4
    ],
    "3a4f84ed": [
      4
    ],
    "2d15dc20": [
      4
    ],
    "797a2fac": [
      4
    ],
    "16c36b38": [
      4
    ],
    "dedfe180": [
      4
    ],
    "1a911913": [
      4
    ],
    "659e6565": [
      4
    ],
    "29f83bac": [
      4
    ],
    "b8f307a4": [
      4
    ],
    "4b2ecd4b": [
      4
    ],
    "b41c516c": [
      4
    ],
    "11fc8016": [
      4
    ],
    "4efcd5e0": [
      4
    ],
    "5bde0357": [
      4
    ],
    "fa6c0ffc": [
      6,
      13,
      14,
      12
    ],
    "035dfd96": [
      6,
      13,
      14,
      12
    ],
    "121acde0": [
      6,
      13,
      14,
      12
    ],
    "4779e3b7": [
      6,
      13,
      14,
      12
    ],
    "c4074bb8": [
      6,
      13,
      14,
      12
    ],
    "a951af46": [
      6,
      13,
      14,
      12
    ],
    "4d1d2e08": [
      6,
      13,
      14,
      12
    ],
    "6559c126": [
      6,
      13,
      14,
      12
    ],
    "26477fc5": [
      6,
      13,
      14,
      12
    ],
    "0d42b708": [
      6,
      13,
      14,
      12
    ],
    "8738ea28": [
      6,
      13,
      14,
      12
    ],
    "3a52f09c": [
      6,
      13,
      14,
      12
    ],
    "182835d3": [
      6,
      13,
      14,
      12
    ],
    "154bb122": [
      6,
      13,
      14,
      12
    ],
    "2771c476": [
      6,
      13,
      14,
      12
    ],
    "65cdfdec": [
      6,
      13,
      14,
      12
    ],
    "a104d2b4": [
      6,
      13,
      14,
      12
    ],
    "2179313e": [
      6,
      13,
      14,
      12
    ],
    "1b5ddb9b": [
      6,
      13,
      14,
      12
    ],
    "2bb91178": [
      4
    ],
    "4952ca6c": [
      4
    ],
    "12eb2f4f": [
      4
    ],
    "03964d83": [
      4
    ],
    "ac903c32": [
      4
    ],
    "fe0d55e0": [
      4
    ],
    "75852e5e": [
      4
    ],
    "16e79594": [
      4
    ],
    "722f47f4": [
      4
    ],
    "3e369b10": [
      4
    ],
    "a3adb078": [
      4
    ],
    "527fdc05": [
      4
    ],
    "d35f1ccc": [
      4
    ],
    "0dc9fd5f": [
      4
    ],
    "738590d3": [
      4
    ],
    "62b4dd70": [
      4
    ],
    "cf4ce5f8": [
      4
    ],
    "428f68b4": [
      4
    ],
    "0a77e069": [
      4
    ],
    "36f5e07d": [
      4
    ],
    "7e17b1e6": [
      4
    ],
    "951e5da4": [
      4
    ],
    "2bd8ab66": [
      4
    ],
    "0994dad6": [
      4
    ],
    "08dbf3aa": [
      4
    ],
    "49e380aa": [
      4
    ],
    "2e56ef98": [
      4
    ],
    "07fc8b42": [
      4
    ],
    "7633800f": [
      4
    ],
    "57f17fe3": [
      4
    ],
    "3dc5c83b": [
      4
    ],
    "5a300e31": [
      4
    ],
    "1215d489": [
      4
    ],
    "3cb5faa6": [
      4
    ],
    "7c0123f6": [
      4
    ],
    "6ac097bb": [
      6,
      13,
      14,
      12
    ],
    "2df78447": [
      6,
      13,
      14,
      12
    ],
    "67e57356": [
      4
    ],
    "16e15af2": [
      4
    ],
    "14e4a518": [
      4
    ],
    "d7b494aa": [
      4
    ],
    "93eb3634": [
      4
    ],
    "4454d47e": [
      4
    ],
    "d34bd85a": [
      4
    ],
    "2f12b842": [
      4
    ],
    "1bd4caba": [
      6,
      13,
      14,
      12
    ],
    "9cb211ba": [
      4
    ],
    "720a9eba": [
      6,
      13,
      14,
      12
    ],
    "31f69e06": [
      6,
      13,
      14,
      12
    ],
    "a3898142": [
      6,
      13,
      14,
      12
    ],
    "35a25071": [
      6,
      13,
      14,
      12
    ],
    "20b0071c": [
      6,
      13,
      14,
      12
    ],
    "2440b700": [
      6,
      13,
      14,
      12
    ],
    "1e1cf0ba": [
      6,
      13,
      14,
      12
    ],
    "2445d786": [
      6,
      13,
      14,
      12
    ],
    "01873488": [
      6,
      13,
      14,
      12
    ],
    "83885bfc": [
      4
    ],
    "3553c2be": [
      4
    ],
    "27dcb194": [
      4
    ],
    "354fc10a": [
      4
    ],
    "27e4a4db": [
      4
    ],
    "21ef3c9a": [
      4
    ],
    "ff189cd4": [
      4
    ],
    "fe54e546": [
      4
    ],
    "6b292445": [
      4
    ],
    "dd032236": [
      4
    ],
    "2bbeca37": [
      4
    ],
    "b1719694": [
      4
    ],
    "c03dd300": [
      4
    ],
    "59e26ba0": [
      4
    ],
    "72edd29e": [
      4
    ],
    "7abc957c": [
      4
    ],
    "ce508ee0": [
      4
    ],
    "03778af2": [
      4
    ],
    "5105d5d3": [
      4
    ],
    "6c198496": [
      4
    ],
    "7731afe6": [
      4
    ],
    "86b20bac": [
      4
    ],
    "65405e59": [
      4
    ],
    "68d7f7fc": [
      4
    ],
    "a68dd130": [
      4
    ],
    "1bd82530": [
      4
    ],
    "39c072bb": [
      4
    ],
    "e1ad1876": [
      4
    ],
    "01014eab": [
      4
    ],
    "fed06bc2": [
      4
    ],
    "22a23606": [
      4
    ],
    "61c89d30": [
      4
    ],
    "bfb0c2ce": [
      4
    ],
    "48d1a41e": [
      4
    ],
    "75f2e69c": [
      4
    ],
    "c105ef48": [
      4
    ],
    "4a7f881b": [
      4
    ],
    "4b15442a": [
      4
    ],
    "96af1c8c": [
      4
    ],
    "ba6d79d2": [
      6,
      13,
      14,
      12
    ],
    "163eb34e": [
      6,
      13,
      14,
      12
    ],
    "f2fa6eba": [
      6,
      13,
      14,
      12
    ],
    "1b45f1cc": [
      6,
      13,
      14,
      12
    ],
    "f3375248": [
      6,
      13,
      14,
      12
    ],
    "cdbd1ece": [
      6,
      13,
      14,
      12
    ],
    "645e103a": [
      6,
      13,
      14,
      12
    ],
    "2922e235": [
      6,
      13,
      14,
      12
    ],
    "c2058098": [
      6,
      13,
      14,
      12
    ],
    "7df11ebb": [
      6,
      13,
      14,
      12
    ],
    "147035c4": [
      6,
      13,
      14,
      12
    ],
    "5fb5756e": [
      6,
      13,
      14,
      12
    ],
    "a435d834": [
      6,
      13,
      14,
      12
    ],
    "533f3e4a": [
      6,
      13,
      14,
      12
    ],
    "e59526e4": [
      6,
      13,
      14,
      12
    ],
    "b235576e": [
      6,
      13,
      14,
      12
    ],
    "698073e0": [
      6,
      13,
      14,
      12
    ],
    "9316bf8a": [
      4
    ],
    "79b93c99": [
      4
    ],
    "3411e050": [
      4
    ],
    "26b04d92": [
      4
    ],
    "5cb0d7f6": [
      4
    ],
    "077f6556": [
      4
    ],
    "8c7bce72": [
      4
    ],
    "32e1cccc": [
      4
    ],
    "da26e9ea": [
      4
    ],
    "6bf2cb0d": [
      4
    ],
    "412e8a18": [
      4
    ],
    "70ff6e80": [
      4
    ],
    "698a2b2a": [
      4
    ],
    "44872e13": [
      4
    ],
    "e7bb5940": [
      4
    ],
    "bd113992": [
      4
    ],
    "7bc28c60": [
      3
    ],
    "367189cc": [
      3
    ],
    "07028c16": [
      3
    ],
    "a096ad30": [
      3
    ],
    "5755362d": [
      3
    ],
    "fa5033dc": [
      2
    ],
    "f0df34d8": [
      2
    ],
    "1c571abc": [
      2
    ],
    "1c685f10": [
      2
    ],
    "3593fd2b": [
      2
    ],
    "0db3775e": [
      10
    ],
    "5209cab5": [
      10
    ],
    "02a54a50": [
      10
    ],
    "69662b5e": [
      10
    ],
    "4f0004ef": [
      10
    ],
    "5a9896a3": [
      9
    ],
    "a695ebba": [
      9
    ],
    "23e1a7b1": [
      9
    ],
    "63b86307": [
      9
    ],
    "1056c5ba": [
      9
    ],
    "628f5b42": [
      5
    ],
    "cc0f7116": [
      5
    ],
    "03f5ac92": [
      5
    ],
    "087d9411": [
      5
    ],
    "61d139e4": [
      5
    ],
    "c8117610": [
      11
    ],
    "9c20c58c": [
      11
    ],
    "25a7217c": [
      11
    ],
    "2fa62c1e": [
      11
    ],
    "589a4505": [
      11
    ]
  },
  "assetsMapping": {
    "1c72762b": [
      "05a4b68.js"
    ],
    "6e246492": [
      "1cf3568.js"
    ],
    "085a35c4": [
      "4667749.js"
    ],
    "856ee714": [
      "496033a.js"
    ],
    "1a3ae26b": [
      "4c23d8c.js"
    ],
    "6fca0322": [
      "8dc57c9.js"
    ],
    "0977d6bc": [
      "a4d87eb.js"
    ],
    "5197e7b5": [
      "b356900.js"
    ],
    "2a130dde": [
      "f4d0dd2.js"
    ]
  }
}